rewiring_package/__init__.py
rewiring_package/get_first_bifurcation.py
rewiring_package/optimise_clustering.py
rewiring_package/optimise_coupling.py
rewiring_package/generate_graphs/__init__.py
rewiring_package/generate_graphs/barabasi_albert.py
rewiring_package/generate_graphs/erdos_renyi.py
rewiring_package/generate_graphs/random_bipartite.py
rewiring_package/generate_graphs/random_geometric.py
rewiring_package/generate_graphs/random_regular.py
rewiring_package/generate_graphs/uniform_graph.py
rewiring_package/generate_graphs/watts_strogatz.py
rewiring_project-2.0.1.dist-info/licenses/LICENSE.txt
rewiring_project-2.0.1.dist-info/METADATA
rewiring_project-2.0.1.dist-info/WHEEL
rewiring_project-2.0.1.dist-info/entry_points.txt
rewiring_project-2.0.1.dist-info/top_level.txt
rewiring_project-2.0.1.dist-info/RECORD
