Metadata-Version: 2.4
Name: rewiring_project
Version: 2.0.1
Summary: All code used in the rewiring project.
Author: Niek Mooij
Author-email: mooij.niek@gmail.com
Classifier: Programming Language :: Python :: 3
Classifier: License :: OSI Approved :: MIT License
Classifier: Operating System :: OS Independent
License-File: LICENSE.txt
Requires-Dist: networkx
Requires-Dist: numpy
Requires-Dist: scipy
Dynamic: author
Dynamic: author-email
Dynamic: classifier
Dynamic: license-file
Dynamic: requires-dist
Dynamic: summary
